[
  {
    "title": "POP-UP PROTEST AT FOUR CORNERS",
    "description": "Come on over to South Street & Electric Avenue for a quick pop-up and feel free to stay longer if you'd like!",
    "month": "June",
    "day": "29",
    "time": "5:00 PM - 6:00 PM",
    "location": "South Street & Electric Avenue, Fitchburg",
    "mapLink": "https://maps.app.goo.gl/vMcXmH891Xfu53u59",
    "facebookLink": "https://www.facebook.com/events/1020038537175428",
    "mobilizeLink": "https://www.mobilize.us/login/?next=/dashboard/indivisible/event/975919"
  },
  {
    "title": "Fitchburg Civic Days block party - volunteer!",
    "description": "Friday, July 3, is the Fitchburg Civic Days block party on Boulder Drive, and Indivisible Fitchburg is hosting a table.",
    "month": "July",
    "day": "3",
    "time": "4:00 PM - 10:00 PM",
    "location": "Boulder Dr., Fitchburg",
    "mapLink": "https://maps.app.goo.gl/tVcYGqrvZHsaAbHd9",
    "facebookLink": "https://www.facebook.com/events/999054942574642",
    "mobilizeLink": "https://www.mobilize.us/indivisible/event/961133"
  },
  {
    "title": "GOOD TROUBLE LIVES ON",
    "description": "Join us for our favorite thing - an overpass standout!",
    "month": "July",
    "day": "18",
    "time": "10:00 PM - 11:30 PM",
    "location": "Park at the Wachusett train station and walk to the overpass",
    "mapLink": "https://maps.app.goo.gl/D293MGWxXeGZDBf1A"
  }
]
